qiniu_django_backend/__init__.py
qiniu_django_backend/backends.py
qiniu_django_backend/utils.py
qiniu_django_backend-1.0.0.dist-info/AUTHORS
qiniu_django_backend-1.0.0.dist-info/METADATA
qiniu_django_backend-1.0.0.dist-info/WHEEL
qiniu_django_backend-1.0.0.dist-info/pbr.json
qiniu_django_backend-1.0.0.dist-info/top_level.txt
qiniu_django_backend-1.0.0.dist-info/RECORD
