Metadata-Version: 2.1
Name: qiniu-django-backend
Version: 1.0.0
Summary: qiniu django backend created by pycman.
Home-page: http://example.com
Author: singein
Author-email: singein@qq.com
License: MIT
Platform: UNKNOWN
Requires-Python: >= 3.6
